[{"name":"luis","pass":"9999","stage":0,"slot":0,"points":0},{"name":"alehff","pass":"qqrum","stage":0,"slot":0,"points":0},{"name":"Bruno","pass":"1234","stage":0,"slot":0,"points":0},{"name":"Juca","pass":"1234","stage":0,"slot":0,"points":0},{"name":"Abner","pass":"1234","stage":0,"slot":0,"points":0},{"name":"bruno","pass":"4444","stage":0,"slot":0,"points":0},{"name":"Rita","pass":"1234","stage":0,"slot":0,"points":0},{"name":"Vera","pass":"1212","stage":0,"slot":0,"points":0},{"name":"ivan","pass":"1234","stage":0,"slot":0,"points":0},{"name":"plinio","pass":"lopiin20","stage":0,"slot":0,"points":0},{"name":"zuc","pass":"asd","stage":0,"slot":0,"points":0},{"name":"asa","pass":"ass","stage":0,"slot":0,"points":0},{"name":"asasa","pass":"asasas","stage":0,"slot":0,"points":0},{"name":"lopiii","pass":"ssss","stage":0,"slot":0,"points":0},{"name":"jucaValente","pass":"oinilp","stage":0,"slot":0,"points":0}]